admin_list_controls/__init__.py
admin_list_controls/actions.py
admin_list_controls/apps.py
admin_list_controls/components.py
admin_list_controls/exceptions.py
admin_list_controls/filters.py
admin_list_controls/selectors.py
admin_list_controls/views.py
admin_list_controls/webpack_manifest.json
admin_list_controls/src/admin_list_controls/actions.js
admin_list_controls/src/admin_list_controls/constants.js
admin_list_controls/src/admin_list_controls/index.js
admin_list_controls/src/admin_list_controls/state.js
admin_list_controls/src/admin_list_controls/styles.scss
admin_list_controls/src/admin_list_controls/components/block.js
admin_list_controls/src/admin_list_controls/components/bound_inputs.js
admin_list_controls/src/admin_list_controls/components/button.js
admin_list_controls/src/admin_list_controls/components/columns.js
admin_list_controls/src/admin_list_controls/components/divider.js
admin_list_controls/src/admin_list_controls/components/icon.js
admin_list_controls/src/admin_list_controls/components/list_controls.js
admin_list_controls/src/admin_list_controls/components/panel.js
admin_list_controls/src/admin_list_controls/components/root.js
admin_list_controls/src/admin_list_controls/components/selector.js
admin_list_controls/src/admin_list_controls/components/summary.js
admin_list_controls/src/admin_list_controls/components/text.js
admin_list_controls/src/admin_list_controls/components/filters/boolean.js
admin_list_controls/src/admin_list_controls/components/filters/choice.js
admin_list_controls/src/admin_list_controls/components/filters/radio.js
admin_list_controls/src/admin_list_controls/components/filters/text.js
admin_list_controls/static/admin_list_controls/dist/admin_list_controls-2a7e7d8d88bf80c15dfe.js
admin_list_controls/static/admin_list_controls/dist/admin_list_controls-2a7e7d8d88bf80c15dfe.js.map
admin_list_controls/templates/admin_list_controls/index.html
admin_list_controls/templates/admin_list_controls/init_index_js.html
wagtail_admin_list_controls-0.1.11.dist-info/LICENSE
wagtail_admin_list_controls-0.1.11.dist-info/METADATA
wagtail_admin_list_controls-0.1.11.dist-info/WHEEL
wagtail_admin_list_controls-0.1.11.dist-info/top_level.txt
wagtail_admin_list_controls-0.1.11.dist-info/RECORD
