Metadata-Version: 2.1
Name: wagtail-admin-list-controls
Version: 0.1.11
Summary: A UI toolkit to build custom filtering and other functionalities into wagtail's admin list views.
Home-page: https://github.com/ixc/wagtail-admin-list-controls
Author: The Interaction Consortium
Author-email: studio@interaction.net.au
License: MIT
Classifier: Environment :: Web Environment
Classifier: Framework :: Django
Classifier: Framework :: Django :: 4.2
Classifier: Framework :: Django :: 5.0
Classifier: Framework :: Wagtail
Classifier: Framework :: Wagtail :: 6
Classifier: Framework :: Wagtail :: 7
Classifier: License :: OSI Approved :: MIT License
Classifier: Operating System :: OS Independent
Classifier: Programming Language :: Python
Classifier: Programming Language :: Python :: 3
Classifier: Programming Language :: Python :: 3.8
Classifier: Programming Language :: Python :: 3.9
Classifier: Programming Language :: Python :: 3.10
Classifier: Programming Language :: Python :: 3.11
Classifier: Programming Language :: Python :: 3.12
Classifier: Topic :: Internet :: WWW/HTTP
Classifier: Topic :: Internet :: WWW/HTTP :: Dynamic Content
License-File: LICENSE
Requires-Dist: Django>=4.2
Requires-Dist: wagtail>=6.0
Requires-Dist: wagtail-modeladmin>=2.0
Provides-Extra: testing
Requires-Dist: django-webtest; extra == "testing"
